python_gpt3_codegen/__init__.py
python_gpt3_codegen-0.1.0.dist-info/LICENSE
python_gpt3_codegen-0.1.0.dist-info/WHEEL
python_gpt3_codegen-0.1.0.dist-info/METADATA
python_gpt3_codegen-0.1.0.dist-info/RECORD
