Metadata-Version: 2.1
Name: python-gpt3-codegen
Version: 0.1.0
Summary: Auto generate code using openapi.
License: MIT
Author: Arijit Basu
Author-email: hi@arijitbasu.in
Requires-Python: >=3.10,<4.0
Classifier: License :: OSI Approved :: MIT License
Classifier: Programming Language :: Python :: 3
Classifier: Programming Language :: Python :: 3.10
Requires-Dist: diskcache (>=5.4.0,<6.0.0)
Requires-Dist: openai (>=0.25.0,<0.26.0)
